traffic_fsm_single.v
module traffic_fsm_single(
    input clk,
    input rst_n,
    output reg [1:0] led, // 00: Red, 01: Green, 10: Yellow
    output reg [5:0] timer_value
);

    reg [1:0] state;
    reg [4:0] counter; // để đếm giây (1Hz)

    // Định nghĩa trạng thái
    localparam S_RED    = 2'b00,
               S_GREEN  = 2'b01,
               S_YELLOW = 2'b10;
    always @(posedge clk or negedge rst_n) begin
        if (!rst_n) begin
            state <= S_RED;
            counter <= 18;
            led <= 2'b00;
            timer_value <= 18;
        end else begin
            case (state)
                S_RED: begin
                    led <= 2'b00;
                    if (counter == 0) begin
                        state <= S_GREEN;
                        counter <= 15;
                    end else begin
                        counter <= counter - 1;
                    end
                end
                S_GREEN: begin
                    led <= 2'b01;
                    if (counter == 0) begin
                        state <= S_YELLOW;
                        counter <= 3;
                    end else begin
                        counter <= counter - 1;
                    end
                end
                S_YELLOW: begin
                    led <= 2'b10;
                    if (counter == 0) begin
                        state <= S_RED;
                        counter <= 18;
                    end else begin
                        counter <= counter - 1;
                    end
                end
                default: begin
                    state <= S_RED;
                    counter <= 18;
                    led <= 2'b00;
                end
            endcase
            timer_value <= counter;
        end
    end

endmodule

traffic_fsm_single_tb.v
`timescale 1ns/1ps
`include "traffic_fsm_single.v"

module traffic_fsm_single_tb;

    reg clk;
    reg rst_n;
    wire [1:0] led;
    wire [5:0] timer_value;


    // Instantiate the DUT (Device Under Test)
    traffic_fsm_single uut (
        .clk(clk),
        .rst_n(rst_n),
        .led(led),
        .timer_value(timer_value)
    );

    // Clock generation: 1Hz = 1s period => toggle every 0.5s = 500,000,000 ns
    // But for simulation, we use faster clock for practicality
    initial begin
        clk = 0;
        forever #5 clk = ~clk; // 100MHz clock (10ns period)
    end

    // Stimulus
    initial begin
        // Dump waveform
        $dumpfile("traffic_fsm_single_tb.vcd");
        $dumpvars(0, traffic_fsm_single_tb);

        // Initial reset
        rst_n = 0;
        #20;         // Wait 20ns
        rst_n = 1;

        // Run simulation for enough time to see all light cycles
        #1000;       // Simulate 1000ns

        $finish;
    end

endmodule

traffic_fsm_single_tb.vcd
$date
	Fri Jun 13 13:40:58 2025
$end
$version
	Icarus Verilog
$end
$timescale
	1ps
$end
$scope module traffic_fsm_single_tb $end
$var wire 6 ! timer_value [5:0] $end
$var wire 2 " led [1:0] $end
$var reg 1 # clk $end
$var reg 1 $ rst_n $end
$scope module uut $end
$var wire 1 # clk $end
$var wire 1 $ rst_n $end
$var parameter 2 % S_GREEN $end
$var parameter 2 & S_RED $end
$var parameter 2 ' S_YELLOW $end
$var reg 5 ( counter [4:0] $end
$var reg 2 ) led [1:0] $end
$var reg 2 * state [1:0] $end
$var reg 6 + timer_value [5:0] $end
$upscope $end
$upscope $end
$enddefinitions $end
$comment Show the parameter values. $end
$dumpall
b10 '
b0 &
b1 %
$end
#0
$dumpvars
b10010 +
b0 *
b0 )
b10010 (
0$
0#
b0 "
b10010 !
$end
#5000
1#
#10000
0#
#15000
1#
#20000
0#
1$
#25000
b10001 (
1#
#30000
0#
#35000
b10001 !
b10001 +
b10000 (
1#
#40000
0#
#45000
b10000 !
b10000 +
b1111 (
1#
#50000
0#
#55000
b1111 !
b1111 +
b1110 (
1#
#60000
0#
#65000
b1110 !
b1110 +
b1101 (
1#
#70000
0#
#75000
b1101 !
b1101 +
b1100 (
1#
#80000
0#
#85000
b1100 !
b1100 +
b1011 (
1#
#90000
0#
#95000
b1011 !
b1011 +
b1010 (
1#
#100000
0#
#105000
b1010 !
b1010 +
b1001 (
1#
#110000
0#
#115000
b1001 !
b1001 +
b1000 (
1#
#120000
0#
#125000
b1000 !
b1000 +
b111 (
1#
#130000
0#
#135000
b111 !
b111 +
b110 (
1#
#140000
0#
#145000
b110 !
b110 +
b101 (
1#
#150000
0#
#155000
b101 !
b101 +
b100 (
1#
#160000
0#
#165000
b100 !
b100 +
b11 (
1#
#170000
0#
#175000
b11 !
b11 +
b10 (
1#
#180000
0#
#185000
b10 !
b10 +
b1 (
1#
#190000
0#
#195000
b1 !
b1 +
b0 (
1#
#200000
0#
#205000
b0 !
b0 +
b1111 (
b1 *
1#
#210000
0#
#215000
b1111 !
b1111 +
b1110 (
b1 "
b1 )
1#
#220000
0#
#225000
b1110 !
b1110 +
b1101 (
1#
#230000
0#
#235000
b1101 !
b1101 +
b1100 (
1#
#240000
0#
#245000
b1100 !
b1100 +
b1011 (
1#
#250000
0#
#255000
b1011 !
b1011 +
b1010 (
1#
#260000
0#
#265000
b1010 !
b1010 +
b1001 (
1#
#270000
0#
#275000
b1001 !
b1001 +
b1000 (
1#
#280000
0#
#285000
b1000 !
b1000 +
b111 (
1#
#290000
0#
#295000
b111 !
b111 +
b110 (
1#
#300000
0#
#305000
b110 !
b110 +
b101 (
1#
#310000
0#
#315000
b101 !
b101 +
b100 (
1#
#320000
0#
#325000
b100 !
b100 +
b11 (
1#
#330000
0#
#335000
b11 !
b11 +
b10 (
1#
#340000
0#
#345000
b10 !
b10 +
b1 (
1#
#350000
0#
#355000
b1 !
b1 +
b0 (
1#
#360000
0#
#365000
b0 !
b0 +
b11 (
b10 *
1#
#370000
0#
#375000
b11 !
b11 +
b10 (
b10 "
b10 )
1#
#380000
0#
#385000
b10 !
b10 +
b1 (
1#
#390000
0#
#395000
b1 !
b1 +
b0 (
1#
#400000
0#
#405000
b0 !
b0 +
b10010 (
b0 *
1#
#410000
0#
#415000
b10010 !
b10010 +
b10001 (
b0 "
b0 )
1#
#420000
0#
#425000
b10001 !
b10001 +
b10000 (
1#
#430000
0#
#435000
b10000 !
b10000 +
b1111 (
1#
#440000
0#
#445000
b1111 !
b1111 +
b1110 (
1#
#450000
0#
#455000
b1110 !
b1110 +
b1101 (
1#
#460000
0#
#465000
b1101 !
b1101 +
b1100 (
1#
#470000
0#
#475000
b1100 !
b1100 +
b1011 (
1#
#480000
0#
#485000
b1011 !
b1011 +
b1010 (
1#
#490000
0#
#495000
b1010 !
b1010 +
b1001 (
1#
#500000
0#
#505000
b1001 !
b1001 +
b1000 (
1#
#510000
0#
#515000
b1000 !
b1000 +
b111 (
1#
#520000
0#
#525000
b111 !
b111 +
b110 (
1#
#530000
0#
#535000
b110 !
b110 +
b101 (
1#
#540000
0#
#545000
b101 !
b101 +
b100 (
1#
#550000
0#
#555000
b100 !
b100 +
b11 (
1#
#560000
0#
#565000
b11 !
b11 +
b10 (
1#
#570000
0#
#575000
b10 !
b10 +
b1 (
1#
#580000
0#
#585000
b1 !
b1 +
b0 (
1#
#590000
0#
#595000
b0 !
b0 +
b1111 (
b1 *
1#
#600000
0#
#605000
b1111 !
b1111 +
b1110 (
b1 "
b1 )
1#
#610000
0#
#615000
b1110 !
b1110 +
b1101 (
1#
#620000
0#
#625000
b1101 !
b1101 +
b1100 (
1#
#630000
0#
#635000
b1100 !
b1100 +
b1011 (
1#
#640000
0#
#645000
b1011 !
b1011 +
b1010 (
1#
#650000
0#
#655000
b1010 !
b1010 +
b1001 (
1#
#660000
0#
#665000
b1001 !
b1001 +
b1000 (
1#
#670000
0#
#675000
b1000 !
b1000 +
b111 (
1#
#680000
0#
#685000
b111 !
b111 +
b110 (
1#
#690000
0#
#695000
b110 !
b110 +
b101 (
1#
#700000
0#
#705000
b101 !
b101 +
b100 (
1#
#710000
0#
#715000
b100 !
b100 +
b11 (
1#
#720000
0#
#725000
b11 !
b11 +
b10 (
1#
#730000
0#
#735000
b10 !
b10 +
b1 (
1#
#740000
0#
#745000
b1 !
b1 +
b0 (
1#
#750000
0#
#755000
b0 !
b0 +
b11 (
b10 *
1#
#760000
0#
#765000
b11 !
b11 +
b10 (
b10 "
b10 )
1#
#770000
0#
#775000
b10 !
b10 +
b1 (
1#
#780000
0#
#785000
b1 !
b1 +
b0 (
1#
#790000
0#
#795000
b0 !
b0 +
b10010 (
b0 *
1#
#800000
0#
#805000
b10010 !
b10010 +
b10001 (
b0 "
b0 )
1#
#810000
0#
#815000
b10001 !
b10001 +
b10000 (
1#
#820000
0#
#825000
b10000 !
b10000 +
b1111 (
1#
#830000
0#
#835000
b1111 !
b1111 +
b1110 (
1#
#840000
0#
#845000
b1110 !
b1110 +
b1101 (
1#
#850000
0#
#855000
b1101 !
b1101 +
b1100 (
1#
#860000
0#
#865000
b1100 !
b1100 +
b1011 (
1#
#870000
0#
#875000
b1011 !
b1011 +
b1010 (
1#
#880000
0#
#885000
b1010 !
b1010 +
b1001 (
1#
#890000
0#
#895000
b1001 !
b1001 +
b1000 (
1#
#900000
0#
#905000
b1000 !
b1000 +
b111 (
1#
#910000
0#
#915000
b111 !
b111 +
b110 (
1#
#920000
0#
#925000
b110 !
b110 +
b101 (
1#
#930000
0#
#935000
b101 !
b101 +
b100 (
1#
#940000
0#
#945000
b100 !
b100 +
b11 (
1#
#950000
0#
#955000
b11 !
b11 +
b10 (
1#
#960000
0#
#965000
b10 !
b10 +
b1 (
1#
#970000
0#
#975000
b1 !
b1 +
b0 (
1#
#980000
0#
#985000
b0 !
b0 +
b1111 (
b1 *
1#
#990000
0#
#995000
b1111 !
b1111 +
b1110 (
b1 "
b1 )
1#
#1000000
0#
#1005000
b1110 !
b1110 +
b1101 (
1#
#1010000
0#
#1015000
b1101 !
b1101 +
b1100 (
1#
